.DS_Store
ontospy/VERSION.py
ontospy/__init__.py
ontospy/cli.py
ontospy/core/__init__.py
ontospy/core/actions.py
ontospy/core/entities.py
ontospy/core/manager.py
ontospy/core/ontospy.py
ontospy/core/rdf_loader.py
ontospy/core/shacl_helper.py
ontospy/core/sparql_helper.py
ontospy/core/utils.py
ontospy/extras/__init__.py
ontospy/extras/shell.py
ontospy/extras/shell_lib.py
ontospy/extras/shell_quotes.py
ontospy/extras/hacks/__init__.py
ontospy/extras/hacks/compare.py
ontospy/extras/hacks/dbpedia.py
ontospy/extras/hacks/gist.py
ontospy/extras/hacks/matcher.py
ontospy/extras/hacks/server.py
ontospy/extras/hacks/sketch.py
ontospy/extras/hacks/sparqlpy.py
ontospy/extras/hacks/turtle-cli.py
ontospy/extras/hacks/vocabsturtleprompt.py
ontospy/gendocs/CONFIG.py
ontospy/gendocs/__init__.py
ontospy/gendocs/actions.py
ontospy/gendocs/jinja_env.py
ontospy/gendocs/utils.py
ontospy/gendocs/viz_factory.py
ontospy/gendocs/media/static/custom/favicon.ico
ontospy/gendocs/media/static/custom/css/familytree.css
ontospy/gendocs/media/static/custom/css/simple-sidebar.css
ontospy/gendocs/media/static/custom/css/sticky-footer-navbar.css
ontospy/gendocs/media/static/custom/css/tabletree.css
ontospy/gendocs/media/static/img/404-error.png
ontospy/gendocs/media/static/img/screenshot-basic-html.png
ontospy/gendocs/media/static/libs/bootstrap-3_3_7-dist/css/bootstrap-theme.css
ontospy/gendocs/media/static/libs/bootstrap-3_3_7-dist/css/bootstrap-theme.css.map
ontospy/gendocs/media/static/libs/bootstrap-3_3_7-dist/css/bootstrap-theme.min.css
ontospy/gendocs/media/static/libs/bootstrap-3_3_7-dist/css/bootstrap-theme.min.css.map
ontospy/gendocs/media/static/libs/bootstrap-3_3_7-dist/css/bootstrap.css
ontospy/gendocs/media/static/libs/bootstrap-3_3_7-dist/css/bootstrap.css.map
ontospy/gendocs/media/static/libs/bootstrap-3_3_7-dist/css/bootstrap.min.css
ontospy/gendocs/media/static/libs/bootstrap-3_3_7-dist/css/bootstrap.min.css.map
ontospy-2.1.1.dist-info/LICENSE
ontospy-2.1.1.dist-info/METADATA
ontospy-2.1.1.dist-info/WHEEL
ontospy-2.1.1.dist-info/entry_points.txt
ontospy-2.1.1.dist-info/top_level.txt
ontospy-2.1.1.dist-info/RECORD
