Metadata-Version: 2.1
Name: ontospy
Version: 2.1.1
Summary: Query, inspect and visualize ontologies encoded via RDF and OWL.
Home-page: https://github.com/lambdamusic/ontospy
Author: Michele Pasin
Author-email: michele.pasin@gmail.com
License: MIT
Keywords: ontology semantic web linked data rdf owl visualization documentation knowledge graph
Platform: UNKNOWN
Classifier: Development Status :: 5 - Production/Stable
Classifier: Intended Audience :: Science/Research
Classifier: Intended Audience :: Developers
Classifier: Topic :: Scientific/Engineering :: Artificial Intelligence
Classifier: License :: OSI Approved :: MIT License
Classifier: Programming Language :: Python :: 3
Classifier: Programming Language :: Python :: 3.2
Classifier: Programming Language :: Python :: 3.3
Classifier: Programming Language :: Python :: 3.4
Classifier: Programming Language :: Python :: 3.5
Classifier: Programming Language :: Python :: 3.6
Classifier: Programming Language :: Python :: 3.7
License-File: LICENSE
Requires-Dist: rdflib
Requires-Dist: SPARQLWrapper
Requires-Dist: html5lib
Requires-Dist: requests
Requires-Dist: pyfiglet
Requires-Dist: click
Requires-Dist: colorama
Requires-Dist: pyparsing
Requires-Dist: jinja2
Requires-Dist: jinja2-time
Requires-Dist: pygments
Provides-Extra: shell
Requires-Dist: readline ; extra == 'shell'
